[


    [
        {
            "imagen": "https://samuelvasquezgonzalez.github.io/API-portf/multimedia/html.png",
            "parrafo": "HTML5: Web Layout"
        },
        {
            "imagen": "https://samuelvasquezgonzalez.github.io/API-portf/multimedia/css.png",
            "parrafo": "CSS3: Web Styles"
        },
        {
            "imagen": "https://samuelvasquezgonzalez.github.io/API-portf/multimedia/js.png",
            "parrafo": "JavaScript: Website Functionality"
        },
        {
            "imagen": "https://samuelvasquezgonzalez.github.io/API-portf/multimedia/react.png",
            "parrafo": "React.js: Library to make user Interfaces"
        }
    ],

    [
        {
            "imagen": "https://samuelvasquezgonzalez.github.io/API-portf/multimedia/ai.png",
            "parrafo": "Ilustrator: Illustrations in Vectorization"
        },
        {
            "imagen": "https://samuelvasquezgonzalez.github.io/API-portf/multimedia/ps.png",
            "parrafo": "Photoshop: Image Edition"
        }
    ],

    [
        {
            "imagen": "https://samuelvasquezgonzalez.github.io/API-portf/multimedia/mysql.png",
            "parrafo": "MySql: Database Manager and Creator"
        }
    ],

    [
        {
            "imagen": "https://samuelvasquezgonzalez.github.io/API-portf/multimedia/git.png",
            "parrafo": "Git: Version Control System"
        },
        {
            "imagen": "https://samuelvasquezgonzalez.github.io/API-portf/multimedia/npm.png",
            "parrafo": "Npm: Node.js Package Manager"
        },
        {
            "imagen": "https://samuelvasquezgonzalez.github.io/API-portf/multimedia/workbench.png",
            "parrafo": "MySql Workbench: MySQL interface"
        }
    ],
    [
        {
            "imagen": "https://samuelvasquezgonzalez.github.io/API-portf/multimedia/node.js",
            "parrafo": "Node.js: Server-side Javascript"
        },
        {
            "imagen": "https://samuelvasquezgonzalez.github.io/API-portf/multimedia/express.png",
            "parrafo": "Express.js: Node.js Framework to make the Endpoints"
        }
    ]
]